Workbook

Sheet 012026
B1: 46023 | C1: 46054 | D1: 46082 | E1: 46113 | F1: 46143 | G1: 46174 | H1: 46204 | I1: 46235 | J1: 46266 | K1: 46296 | L1: 46327 | M1: 46357
A2: DETALLE CALCULO GANANCIAS 2026
A5: Tope cargas sociales Enero 2026 | B5: 3823373
A6: Tope cargas sociales Febrero 2026 | B6: 3932339.1
A7: SAC | C7: =B4*A4*0.17 -> 0
A16: Tope cargas sociales Marzo 2026 | B16: 4045590.5
A17: Tope cargas sociales Abril 2026 | B17: 3128545.7
A18: Tope cargas sociales Mayo 2026 | B18: 3245240.5
A19: Tope cargas sociales Junio 2026 | B19: 3335458.2 | C19: =B19/2 -> 1667729.1
A20: Tope cargas sociales Julio 2026 | B20: 3385490
A21: Tope cargas sociales AGOSTO 2026 | B21: 3440335 | C21: =B21/2 -> 1720167.5
A22: Tope cargas sociales SEPTIEMBRE 2026 | B22: 3505701.4
A23: Tope cargas sociales OCTUBRE 2026 | B23: 3571608.5
A24: Tope cargas sociales NOVIEMBRE 2026 | B24: 3645898 | G24: vac
A25: Tope cargas sociales DICIEMBRE 2026 | B25: 3731212 | C25: =B25/2 -> 1865606 | G25: =G28/7 -> 0
B26: 46023 | C26: 46054 | D26: 46082 | E26: 46113 | F26: 46143 | G26: 46174 | H26: 46204 | I26: 46235 | J26: 46266 | K26: 46296 | L26: 46327 | M26: 46357
A27: Sueldo bruto | B27: 3835388 | C27: =B27 -> 3835388 | D27: =C27 -> 3835388 | E27: =D27 -> 3835388 | F27: =E27 -> 3835388 | G27: =F27 -> 3835388 | H27: =G27 -> 3835388 | I27: =H27 -> 3835388 | J27: =I27 -> 3835388 | ... M27: =L27 -> 3835388 | N27: =SUM(B27:M27) -> 46024656
A28: Plus vacaciones | B28: 178984.77 | N28: =SUM(B28:M28) -> 178984.77
A29: SAC REAL | G29: =G27/2 -> 1917694 | M29: =M27/2 -> 1917694 | N29: =SUM(B29:M29) -> 3835388
A30: SAC Prorrateado | B30: =(B27)/12 -> 319615.67 | C30: =(C27)/12 -> 319615.67 | D30: =(D27)/12 -> 319615.67 | E30: =(E27)/12 -> 319615.67 | F30: =(F27)/12 -> 319615.67 | H30: =(H27)/12 -> 319615.67 | I30: =(I27)/12 -> 319615.67 | J30: =(J27)/12 -> 319615.67 | K30: =(K27)/12 -> 319615.67 | L30: =(L27)/12 -> 319615.67 | N30: =SUM(B30:M30) -> 3196156.7
B31: =+B27+B30 -> 4155003.7 | C31: =+C27+C30 -> 4155003.7 | D31: =+D27+D30 -> 4155003.7 | E31: =SUM(E27:E30) -> 4155003.7 | F31: =+F27+F30 -> 4155003.7 | G31: =SUM(G27:G30) -> 5753082 | H31: =+H27+H30 -> 4155003.7 | I31: =SUM(I27:I30) -> 4155003.7 | J31: =SUM(J27:J30) -> 4155003.7 | K31: =+K27+K30 -> 4155003.7 | L31: =+L27+L30 -> 4155003.7 | M31: =SUM(M27:M30) -> 5753082 | N31: =SUM(B31:M31) -> 53056201
A32: art 26 gravado en su totalidad | N32: =SUM(B32:M32) -> 0
A33: BONO | N33: =SUM(B33:M33) -> 0
A37: Sub Total Ganancia Bruta | B37: =B33+B27 -> 3835388 | C37: =C33+C27 -> 3835388 | D37: =D33+D27 -> 3835388 | E37: =E33+E27 -> 3835388 | F37: =F33+F27 -> 3835388 | G37: =G33+G27 -> 3835388 | H37: =H33+H27 -> 3835388 | I37: =I33+I27 -> 3835388 | ... M37: =M33+M27 -> 3835388 | N37: =SUM(B37:M37) -> 46024656
N38: =SUM(B38:M38) -> 0
A39: Jubilac. | B39: =-B5*11% -> -420571.02 | C39: =-C27*11% -> -421892.68 | D39: =-B16*11% -> -445014.95 | E39: =-B17*11% -> -344140.03 | F39: =-B18*11% -> -356976.45 | G39: =-B19*0.11 -> -366900.4 | H39: =-B20*11% -> -372403.91 | I39: =-B21*0.11 -> -378436.85 | J39: =-B22*0.11 -> -385627.15 | K39: =-B23*0.11 -> -392876.94 | L39: =-B24*0.11 -> -401048.78 | M39: =-B25*0.11 -> -410433.32 | N39: =SUM(B39:M39) -> -4696322.5
A40: Ley 19032 | B40: =-B5*3% -> -114701.19 | C40: =-C27*3% -> -115061.64 | D40: =-B16*3% -> -121367.71 | E40: =-B17*3% -> -93856.372 | F40: =-B18*3% -> -97357.215 | G40: =-B19*0.03 -> -100063.75 | H40: =-B20*3% -> -101564.7 | I40: =-B21*0.03 -> -103210.05 | J40: =-B22*0.03 -> -105171.04 | K40: =-B23*0.03 -> -107148.26 | L40: =-B24*0.03 -> -109376.94 | M40: =-B25*0.03 -> -111936.36 | N40: =SUM(B40:M40) -> -1280815.2
A41: Obra social | B41: =-B5*3% -> -114701.19 | C41: =C40 -> -115061.64 | D41: =-B16*3% -> -121367.71 | E41: =-B17*3% -> -93856.372 | F41: =-B18*3% -> -97357.215 | G41: =G40 -> -100063.75 | H41: =-B20*3% -> -101564.7 | I41: =-B21*0.03 -> -103210.05 | J41: =J40 -> -105171.04 | K41: =K40 -> -107148.26 | L41: =L40 -> -109376.94 | M41: =M40 -> -111936.36 | N41: =SUM(B41:M41) -> -1280815.2
N42: =SUM(B42:M42) -> 0
A43: Total Descuentos | B43: =SUM(B39:B42) -> -649973.4 | C43: =SUM(C39:C42) -> -652015.96 | D43: =SUM(D39:D42) -> -687750.38 | E43: =SUM(E39:E42) -> -531852.77 | F43: =SUM(F39:F42) -> -551690.88 | G43: =SUM(G39:G42) -> -567027.89 | H43: =SUM(H39:H42) -> -575533.31 | I43: =SUM(I39:I42) -> -584856.95 | ... M43: =SUM(M39:M42) -> -634306.04 | N43: =SUM(B43:M43) -> -7257952.9
N44: =SUM(B44:M44) -> 0
A45: Ingresos gravados (menos SAC) | B45: =B27++B33 -> 3835388 | C45: =C27+B45 -> 7670776 | D45: =D27+C45 -> 11506164 | E45: =E27+D45 -> 15341552 | F45: =F27+E45 -> 19176940 | G45: =G27+F45 -> 23012328 | H45: =H27+G45 -> 26847716 | I45: =I27+H45 -> 30683104 | J45: =J27+I45 -> 34518492 | ... M45: =M27+L45 -> 46024656 | N45: =SUM(B45:M45) -> 299160264
N46: =SUM(B46:M46) -> 0
A47: Prorrateo vacaciones | B47: =+B28/12 -> 14915.398 | C47: =$B$47+B47 -> 29830.796 | D47: =$B$47+C47 -> 44746.193 | E47: =$B$47+D47 -> 59661.591 | F47: =$B$47+E47 -> 74576.989 | G47: =$B$47+F47 -> 89492.387 | H47: =$B$47+G47 -> 104407.78 | I47: =$B$47+H47 -> 119323.18 | J47: =$B$47+I47 -> 134238.58 | ... M47: =$B$47+L47 -> 178984.77 | N47: =M47 -> 178984.77
A48: Descuentos | N48: =SUM(B48:M48) -> 0
B49: =SUM(B47:B48) -> 14915.398 | C49: =SUM(C47:C48) -> 29830.796 | D49: =SUM(D47:D48) -> 44746.193 | E49: =SUM(E47:E48) -> 59661.591 | F49: =SUM(F47:F48) -> 74576.989 | G49: =SUM(G47:G48) -> 89492.387 | H49: =SUM(H47:H48) -> 104407.78 | I49: =SUM(I47:I48) -> 119323.18 | ... M49: =SUM(M47:M48) -> 178984.77 | N49: =SUM(B49:M49) -> 1163401
A52: Ingresos Gravados Acumulados SUELDO MAS VACACIONES | B52: =B45+B47 -> 3850303.4 | C52: =C45+C47 -> 7700606.8 | D52: =D45+D47 -> 11550910 | E52: =E45+E47 -> 15401214 | F52: =F45+F47 -> 19251517 | G52: =G45+G47 -> 23101820 | H52: =H45+H47 -> 26952124 | I52: =I45+I47 -> 30802427 | ... M52: =M45+M47 -> 46203641 | N52: =M52 -> 46203641
A54: Ajuste al neto SAC | B54: =-B30+B61 -> -265451.22 | C54: =-C30+C61 -> -265281 | D54: =-D30+D61 -> -262303.14 | E54: =-E30+E61 -> -275294.6 | F54: =-F30+F61 -> -273641.43 | G54: =C19*0.17+-G29-SUM(B54:F54) -> -292208.67 | H54: =-H30+H61 -> -271654.56 | I54: =-I30+I61 -> -270877.59 | J54: =-J30+J61 -> -269951.56 | K54: =-K30+K61 -> -269017.88 | L54: =-L30+L61 -> -267965.45 | M54: =C25*0.17+-M29-SUM(H54:L54) -> -251073.95 | N54: SAC DIC
A55: Ajuste al neto SAC ACUM | B55: =B54 -> -265451.22 | C55: =C54+B55 -> -530732.22 | D55: =D54+C55 -> -793035.36 | E55: =E54+D55 -> -1068330 | F55: =F54+E55 -> -1341971.4 | G55: =G54+F55 -> -1634180.1 | H55: =H54+G55 -> -1905834.6 | I55: =I54+H55 -> -2176712.2 | J55: =J54+I55 -> -2446663.8 | ... M55: =M54+L55 -> -3234721 | N55: =-#REF!+#REF! -> #REF!
A56: ajuste neto sac 1 a 5 2024 según rg 5531 art 1 k
A57: TOTAL CARGAS | B57: =B48+B43 -> -649973.4 | C57: =C48+C43 -> -652015.96 | D57: =D48+D43 -> -687750.38 | E57: =E48+E43 -> -531852.77 | F57: =F48+F43 -> -551690.88 | G57: =G48+G43 -> -567027.89 | H57: =H48+H43 -> -575533.31 | I57: =I48+I43 -> -584856.95 | ... M57: =M48+M43 -> -634306.04 | N57: SAC JUNIO
A58: cargas sac real | N58: =G55 -> -1634180.1
A59: CARGAS ACUM | B59: =B43 -> -649973.4 | C59: =C43+B59+C48 -> -1301989.4 | D59: =D43+C59+D48 -> -1989739.7 | E59: =E43+D59 -> -2521592.5 | F59: =F43+E59-+$A$50 -> -3073283.4 | G59: =G43+F59-+$A$50 -> -3640311.3 | H59: =H43+G59-+$A$50 -> -4215844.6 | I59: =I43+H59-+$A$50 -> -4800701.5 | J59: =J43+I59-+$A$50 -> -5396670.8 | K59: =K43+J59-+$A$50 -> -6003844.2 | L59: =L43+K59-+$A$50 -> -6623646.9 | M59: =M43+L59-+$A$50 -> -7257952.9
A61: CARGAS SOC SAC | B61: =+(($B$5/12*0.17)) -> 54164.45 | C61: =((C30*0.17)) -> 54334.663 | D61: =((B16/12*0.17)) -> 57312.531 | E61: =((B17/12*0.17)) -> 44321.065 | F61: =((B18/12*0.17)) -> 45974.24 | G61: =C19*0.17-SUM(B61:F61) -> 27406.996 | H61: =B20/12*0.17 -> 47961.109 | I61: =B21/12*0.17 -> 48738.079 | J61: =B22/12*0.17 -> 49664.102 | K61: =B23/12*0.17 -> 50597.788 | L61: =B24/12*0.17 -> 51650.222 | M61: =C25*0.17-SUM(H61:L61) -> 68541.721
A62: Ganancia neta mensual SDO VAC Y SAC MENOS CARGAS | B62: =B27+B47+B43+B48-B54+B33 -> 3465781.2 | C62: =C27+C47+C43+C48-C54+C33 -> 3478483.8 | D62: =D27+D47+D43+D48-D54+D33 -> 3454687 | E62: =E27+E47+E43+E48-E54+E33-D47 -> 3593745.2 | F62: =F27+F47+F43+F48-F54+F33-E47 -> 3572253.9 | G62: =G27+G47+G43+G48-G54+G33-F47 -> 3575484.2 | H62: =H27+H47+H43+H48-H54+H33-G47 -> 3546424.6 | I62: =I27+I47+I43+I48-I54+I33-H47 -> 3536324 | J62: =J27+J47+J43+J48-J54+J33-I47 -> 3524285.7 | K62: =K27+K47+K43+K48-K54+K33-J47 -> 3512147.8 | L62: =L27+L47+L43+L48-L54+L33-K47 -> 3498466.2 | M62: =M27+M47+M43+M48-M54+M33-L47 -> 3467071.3 | N62: =SUM(B62:M62) -> 42225155
A64: Ganancia Neta acumulada | B64: =B62 -> 3465781.2 | C64: =C45+C47-C55+C57+B59 -> 6929349.7 | D64: =D45+D47-D55+D59 -> 10354206 | E64: =E45+E47-E55+E57+D59-+D48 -> 13947951 | F64: =F45+F47-F55+F57+E59-+E48 -> 17520205 | G64: =G45+G47-G55+G57+F59-+F48 -> 21095689 | H64: =H45+H47-H55+H57+G59-+G48 -> 24642114 | I64: =I45+I47-I55+I57+H59-+H48 -> 28178438 | J64: =J45+J47-J55+J57+I59-+I48 -> 31702724 | K64: =K45+K47-K55+K57+J59-+J48 -> 35214871 | L64: =L45+L47-L55+L57+K59-+K48 -> 38713338 | M64: =M45+M47-M55+M57+L59-+L48 -> 42180409 | N64: =M64 -> 42180409
A68: Cuota Medico asistencial
A69: tope 5% de gcia neta del ejercicio acumulada | B69: =B83*5/100 -> 38412.009 | C69: =C84*5/100 -> 76713.379 | D69: =D84*5/100 -> 113079.14 | E69: =E84*5/100 -> 157889.35 | F69: =F84*5/100 -> 201624.99 | G69: =G84*5/100 -> 245522.15 | H69: =H84*5/100 -> 287966.33 | I69: =I84*5/100 -> 329905.48 | J69: =J84*5/100 -> 371242.71 | ... M69: =M84*5/100 -> 490495.82 | N69: =SUM(B69:M69) -> 3176843.7
A70: Deducciones | N70: =SUM(B70:M70) -> 0
A71: Ganancia no Imponible | B71: ='Tablas '!B3 -> 429316.88 | C71: ='Tablas '!C3 -> 858633.75 | D71: ='Tablas '!D3 -> 1287950.6 | E71: ='Tablas '!E3 -> 1717267.5 | F71: ='Tablas '!F3 -> 2146584.4 | G71: ='Tablas '!G3 -> 2575901.2 | H71: ='Tablas '!H3 -> 3005218.1 | I71: ='Tablas '!I3 -> 3434535 | ... M71: ='Tablas '!M3 -> 5151802.5 | N71: =M71 -> 5151802.5
A72: Deducción especial | B72: ='Tablas '!B4 -> 2060721 | C72: ='Tablas '!C4 -> 4121442 | D72: ='Tablas '!D4 -> 6182163 | E72: ='Tablas '!E4 -> 8242884 | F72: ='Tablas '!F4 -> 10303605 | G72: ='Tablas '!G4 -> 12364326 | H72: ='Tablas '!H4 -> 14425047 | I72: ='Tablas '!I4 -> 16485768 | ... M72: ='Tablas '!M4 -> 24728652 | N72: =M72 -> 24728652
A73: conyuge | N73: =M73 -> 0
A74: Cuota Medico asistencial | N74: =M74 -> 0
A75: Empleada Doméstica | N75: =M75 -> 0
A76: Deduccion SAC especial | B76: =SUM(B71:B75)/12 -> 207503.16 | C76: =SUM(C71:C75)/12 -> 415006.31 | D76: =SUM(D71:D75)/12 -> 622509.47 | E76: =SUM(E71:E75)/12 -> 830012.63 | F76: =SUM(F71:F75)/12 -> 1037515.8 | G76: =SUM(G71:G75)/12 -> 1245018.9 | H76: =SUM(H71:H75)/12 -> 1452522.1 | I76: =SUM(I71:I75)/12 -> 1660025.3 | ... M76: =SUM(M71:M75)/12 -> 2490037.9 | N76: =M76 -> 2490037.9
A77: Sub Total Deducciones Personales | B77: =SUM(B71:B76) -> 2697541 | C77: =SUM(C71:C76) -> 5395082.1 | D77: =SUM(D71:D76) -> 8092623.1 | E77: =SUM(E71:E76) -> 10790164 | F77: =SUM(F71:F76) -> 13487705 | G77: =SUM(G71:G76) -> 16185246 | H77: =SUM(H71:H76) -> 18882787 | I77: =SUM(I71:I76) -> 21580328 | ... M77: =SUM(M71:M76) -> 32370492 | N77: =M77 -> 32370492
N78: =SUM(B78:M78) -> 0
A79: Ded. Increm. 1er. Parr. | N79: =SUM(B79:M79) -> 0
A80: Ded. Increm. 2do. Parr. | N80: =SUM(B80:M80) -> 0
A81: Ded. Especial decreto 652/2024 | N81: =SUM(B81:M81) -> 0
A83: Gcia Neta Suj a Imp acumulada antes de osde | B83: =B64-B77+B68 -> 768240.18 | C83: =C64-C77+C68 -> 1534267.6 | D83: =D64-D77+D68 -> 2261582.7 | E83: =E64-E77+E68 -> 3157786.9 | F83: =F64-F77+F68 -> 4032499.8 | G83: =G64-G77+G68 -> 4910443 | H83: =H64-H77+H68 -> 5759326.6 | I83: =I64-I77+I68 -> 6598109.6 | ... N83: =N64-N77+N68 -> 9809916.5
A84: Ganancia Neta Sujeta a Impuesto acumulada | B84: =B64-B77 -> 768240.18 | C84: =IF((C64-C77)>=0,C64-C77,0) -> 1534267.6 | D84: =IF((D64-D77)>=0,D64-D77,0) -> 2261582.7 | E84: =IF((E64-E77)>=0,E64-E77,0) -> 3157786.9 | F84: =IF((F64-F77)>=0,F64-F77,0) -> 4032499.8 | G84: =IF((G64-G77)>=0,G64-G77,0) -> 4910443 | H84: =IF((H64-H77)>=0,H64-H77,0) -> 5759326.6 | I84: =IF((I64-I77)>=0,I64-I77,0) -> 6598109.6 | J84: =IF((J64-J77)>=0,J64-J77,0) -> 7424854.3 | ... N84: =IF((N64-N77)>=0,N64-N77,0) -> 9809916.5
A85: =A62 -> Ganancia neta mensual SDO VAC Y SAC MENOS CARGAS | B85: =B84 -> 768240.18 | C85: =C62 -> 3478483.8 | D85: =D62 -> 3454687 | E85: =E62 -> 3593745.2 | F85: =F62 -> 3572253.9 | G85: =G62 -> 3575484.2 | H85: =H62 -> 3546424.6 | I85: =I62 -> 3536324 | J85: =J62 -> 3524285.7 | ... N85: =N62 -> 42225155
A86: Base Imponible | B86: =B85 -> 768240.18 | C86: =C84 -> 1534267.6 | D86: =D84 -> 2261582.7 | E86: =E84 -> 3157786.9 | F86: =F84 -> 4032499.8 | G86: =G84 -> 4910443 | H86: =H84 -> 5759326.6 | I86: =I84 -> 6598109.6 | J86: =J84 -> 7424854.3 | ... N86: =N84 -> 9809916.5
B89: 1 | C89: 2 | D89: 3 | E89: 4 | F89: 5 | G89: 6 | H89: 7 | I89: 8 | J89: 9 | K89: 10 | L89: 11 | M89: 12 | N89: =SUM(B89:M89) -> 78
A90: Impuesto (Anual) | B90: =IF(B86>0,(VLOOKUP(B86,Escalas!$A$19:$E$27,3)),0) -> 80834.55 | C90: =IF(C86>0,(VLOOKUP(C86,Escalas!A29:E37,3)),0) -> 161669.1 | D90: =IF(D86>0,(VLOOKUP(D86,Escalas!A38:E47,3)),0) -> 242503.65 | E90: =IF(E86>0,(VLOOKUP(E86,Escalas!A48:E57,3)),0) -> 323338.2 | F90: =IF(F86>0,(VLOOKUP(F86,Escalas!A58:E67,3)),0) -> 404172.75 | G90: =IF(G86>0,(VLOOKUP(G86,Escalas!A68:E77,3)),0) -> 485007.3 | H90: =IF(H86>0,(VLOOKUP(H86,Escalas!A78:E87,3)),0) -> 439415.31 | I90: =IF(I86>0,(VLOOKUP(I86,Escalas!A88:E97,3)),0) -> 510140.5 | J90: =IF(J86>0,(VLOOKUP(J86,Escalas!A98:E107,3)),0) -> 580865.68 | K90: =IF(K86>0,(VLOOKUP(K86,Escalas!A108:E117,3)),0) -> 651590.86 | L90: =IF(L86>0,(VLOOKUP(L86,Escalas!A118:E127,3)),0) -> 722316.05 | M90: =IF(M86>0,(VLOOKUP(M86,Escalas!A128:E137,3)),0) -> 793041.23 | N90: =IF(N86>0,(VLOOKUP(N86,Escalas!A128:E137,3)),0) -> 793041.23
A91: Porcentaje | B91: =IF(B86>0,VLOOKUP(B86,Escalas!$A$19:$E$27,4),0) -> 0.19 | C91: =IF(C86>0,VLOOKUP(C86,Escalas!A29:E37,4),0) -> 0.19 | D91: =IF(D86>0,VLOOKUP(D86,Escalas!A38:E47,4),0) -> 0.19 | E91: =IF(E86>0,VLOOKUP(E86,Escalas!A48:E57,4),0) -> 0.19 | F91: =IF(F86>0,VLOOKUP(F86,Escalas!A58:E67,4),0) -> 0.19 | G91: =IF(G86>0,VLOOKUP(G86,Escalas!A68:E77,4),0) -> 0.19 | H91: =IF(H86>0,VLOOKUP(H86,Escalas!A78:E87,4),0) -> 0.19 | I91: =IF(I86>0,VLOOKUP(I86,Escalas!A88:E97,4),0) -> 0.19 | J91: =IF(J86>0,VLOOKUP(J86,Escalas!A98:E107,4),0) -> 0.19 | K91: =IF(K86>0,VLOOKUP(K86,Escalas!A108:E117,4),0) -> 0.19 | L91: =IF(L86>0,VLOOKUP(L86,Escalas!A118:E127,4),0) -> 0.19 | M91: =IF(M86>0,VLOOKUP(M86,Escalas!A128:E137,4),0) -> 0.19 | N91: =IF(N86>0,VLOOKUP(N86,Escalas!A128:E137,4),0) -> 0.19
A92: Sobre excedente de | B92: =IF(B86>0,(VLOOKUP(B$86,Escalas!$A$19:$E$27,5)*B89),0) -> 750011.28 | C92: =IF(C86>0,(VLOOKUP(C$86,Escalas!A29:E37,5)),0) -> 1500022.6 | D92: =IF(D86>0,(VLOOKUP(D$86,Escalas!A38:E47,5)),0) -> 2250033.9 | E92: =IF(E86>0,(VLOOKUP(E$86,Escalas!A48:E57,5)),0) -> 3000045.1 | F92: =IF(F86>0,(VLOOKUP(F$86,Escalas!A58:E67,5)),0) -> 3750056.4 | G92: =IF(G86>0,(VLOOKUP(G$86,Escalas!A68:E77,5)),0) -> 4500067.7 | H92: =IF(H86>0,(VLOOKUP(H$86,Escalas!A78:E87,5)),0) -> 4077049.3 | I92: =IF(I86>0,(VLOOKUP(I$86,Escalas!A88:E97,5)),0) -> 4733262.3 | J92: =IF(J86>0,(VLOOKUP(J$86,Escalas!A98:E107,5)),0) -> 5389475.4 | K92: =IF(K86>0,(VLOOKUP(K$86,Escalas!A108:E117,5)),0) -> 6045688.4 | L92: =IF(L86>0,(VLOOKUP(L$86,Escalas!A118:E127,5)),0) -> 6701901.5 | M92: =IF(M86>0,(VLOOKUP(M$86,Escalas!A128:E137,5)),0) -> 7358114.5 | N92: =IF(N86>0,(VLOOKUP(N$86,Escalas!A128:E137,5)),0) -> 7358114.5
N93: =SUM(B93:M93) -> 0
A94: Base cálculo | B94: =IF(B86>0,+B86-B92,0) -> 18228.9 | C94: =IF(C86>0,+C86-C92,0) -> 34245.018 | D94: =IF(D86>0,+D86-D92,0) -> 11548.861 | E94: =IF(E86>0,+E86-E92,0) -> 157741.77 | F94: =IF(F86>0,+F86-F92,0) -> 282443.39 | G94: =IF(G86>0,+G86-G92,0) -> 410375.26 | H94: =IF(H86>0,+H86-H92,0) -> 1682277.3 | I94: =IF(I86>0,+I86-I92,0) -> 1864847.2 | ... N94: =IF(N86>0,+N86-N92,0) -> 2451802
A95: % calculado | B95: =+B91*B94 -> 3463.491 | C95: =+C91*C94 -> 6506.5534 | D95: =+D91*D94 -> 2194.2837 | E95: =+E91*E94 -> 29970.937 | F95: =+F91*F94 -> 53664.244 | G95: =+G91*G94 -> 77971.299 | H95: =+H91*H94 -> 319632.68 | I95: =+I91*I94 -> 354320.97 | ... N95: =+N91*N94 -> 465842.37
A97: TOTAL IMPUESTO ANUAL | B97: =+B90+B95 -> 84298.041 | C97: =+C90+C95 -> 168175.65 | D97: =+D90+D95 -> 244697.93 | E97: =+E90+E95 -> 353309.14 | F97: =+F90+F95 -> 457836.99 | G97: =+G90+G95 -> 562978.6 | H97: =+H90+H95 -> 759047.99 | I97: =+I90+I95 -> 864461.47 | ... N97: =+N90+N95 -> 1258883.6
A98: Anterior | B98: 0 | C98: =+B99 -> 84298.041 | D98: =+C99 -> 168175.65 | E98: =+D99 -> 244697.93 | F98: =+E99 -> 353309.14 | G98: =+F99 -> 457836.99 | H98: =+G99 -> 562978.6 | I98: =+H99 -> 759047.99 | J98: =+I99 -> 864461.47 | ... M98: =+L99 -> 1166628.1 | N98: =M99 -> 1258883.6
A99: Acumulado | B99: =+B103 -> 84298.041 | C99: =+B99+C103 -> 168175.65 | D99: =+C99+D103 -> 244697.93 | E99: =+D99+E103 -> 353309.14 | F99: =+E99+F103 -> 457836.99 | G99: =+F99+G103 -> 562978.6 | H99: =+G99+H103 -> 759047.99 | I99: =+H99+I103 -> 864461.47 | J99: =+I99+J103 -> 967587.67 | ... M99: =+L99+M103 -> 1258883.6 | N99: =SUM(B103:M103) -> 1258883.6
A100: Impuesto Retenido por método Imp Cedular (pago a cuenta) Decreto 652/2024 | H100: =SUM(B100:G100) -> 0 | N100: =SUM(B100:M100) -> 0
A101: Diferencia 2024 (Junio) por Cambio de método | N101: =SUM(B101:M101) -> 0
A102: A favor empleado, se devuelve en liq anual 2024 ver normativa actualizada | N102: =SUM(B102:M102) -> 0
A103: Impuesto Mes | B103: =+B97 -> 84298.041 | C103: =IF(C27<>0,C97-B99,0) -> 83877.612 | D103: =IF(D27<>0,D97-C99,0) -> 76522.28 | E103: =IF(E27<>0,E97-D99,0) -> 108611.2 | F103: =IF(F27<>0,F97-E99,0) -> 104527.86 | G103: =IF(G27<>0,G97-F99,0) -> 105141.6 | H103: =IF(H27<>0,H97-G99,0) -> 196069.39 | I103: =IF(I27<>0,I97-H99,0) -> 105413.48 | J103: =IF(J27<>0,J97-I99,0) -> 103126.2 | ... M103: =IF(M27<>0,M97-L99,0) -> 92255.453 | N103: =SUM(B103:M103) -> 1258883.6
A104: Impuesto Mes considerando saldo a favor | N104: =SUM(B104:M104) -> 0

Sheet Escalas
A3: GANANCIA NETA ACUMULADA | C3: PAGARAN
A4: MAS DE $ | B4: A $ | C4: $ | D4: MAS EL % | E4: S/EXCEDENTE DE
A5: 0 | B5: 1520371.7 | C5: 0 | D5: 5 | E5: 0
A6: 1520371.7 | B6: 3040743.3 | C6: 76018.58 | D6: 9 | E6: 1520371.7
A7: 3040743.3 | B7: 4561115 | C7: 212852.03 | D7: 12 | E7: 3040743.3
A8: 4561115 | B8: 6841672.5 | C8: 395296.63 | D8: 15 | E8: 4561115
A9: 6841672.5 | B9: 13683345 | C9: 737380.26 | D9: 19 | E9: 6841672.5
A10: 13683345 | B10: 20525018 | C10: 2037298 | D10: 23 | E10: 13683345
A11: 20525018 | B11: 30787526 | C11: 3610882.7 | D11: 27 | E11: 20525018
A12: 30787526 | B12: 46181290 | C12: 6381760.1 | D12: 31 | E12: 30787526
A13: 46181290 | B13: en adelante | C13: 11153827 | D13: 35 | E13: 46181290
A17: 20
A18: 1 | B18: 1 | C18: 1 | D18: 1 | E18: 1
A19: 0 | B19: 166669.17 | C19: 0 | D19: 0.05 | E19: 0
A20: 166669.17 | B20: 333338.35 | C20: 8333.46 | D20: 0.09 | E20: 166669.17
A21: 333338.35 | B21: 500007.52 | C21: 23333.68 | D21: 0.12 | E21: 333338.35
A22: 500007.52 | B22: 750011.28 | C22: 43333.99 | D22: 0.15 | E22: 500007.52
A23: 750011.28 | B23: 1500022.6 | C23: 80834.55 | D23: 0.19 | E23: 750011.28
A24: 1500022.6 | B24: 2250033.9 | C24: 223336.69 | D24: 0.23 | E24: 1500022.6
A25: 2250033.9 | B25: 3375050.8 | C25: 395839.29 | D25: 0.27 | E25: 2250033.9
A26: 3375050.8 | B26: 5062576.2 | C26: 699593.86 | D26: 0.31 | E26: 3375050.8
A27: 5062576.2 | B27: en adelante | C27: 1222726.7 | D27: 0.35 | E27: 5062576.2
A28: =+A18+1 -> 2 | B28: =+B18+1 -> 2 | C28: =+C18+1 -> 2 | E28: =+E18+1 -> 2
A29: 0 | B29: 333338.35 | C29: 0 | D29: 0.05 | E29: 0
A30: 333338.35 | B30: 666676.69 | C30: 16666.92 | D30: 0.09 | E30: 333338.35
A31: 666676.69 | B31: 1000015 | C31: 46667.37 | D31: 0.12 | E31: 666676.69
A32: 1000015 | B32: 1500022.6 | C32: 86667.97 | D32: 0.15 | E32: 1000015
A33: 1500022.6 | B33: 3000045.1 | C33: 161669.1 | D33: 0.19 | E33: 1500022.6
A34: 3000045.1 | B34: 4500067.7 | C34: 446673.39 | D34: 0.23 | E34: 3000045.1
A35: 4500067.7 | B35: 6750101.5 | C35: 791678.58 | D35: 0.27 | E35: 4500067.7
A36: 6750101.5 | B36: 10125152 | C36: 1399187.7 | D36: 0.31 | E36: 6750101.5
A37: 10125152 | B37: en adelante | C37: 2445453.5 | D37: 0.35 | E37: 10125152
A38: =+A28+1 -> 3 | B38: =+B28+1 -> 3 | C38: =+C28+1 -> 3 | E38: =+E28+1 -> 3
A39: 0 | B39: 500007.52 | C39: 0 | D39: 0.05 | E39: 0
A40: 500007.52 | B40: 1000015 | C40: 25000.38 | D40: 0.09 | E40: 500007.52
A41: 1000015 | B41: 1500022.6 | C41: 70001.05 | D41: 0.12 | E41: 1000015
A42: 1500022.6 | B42: 2250033.9 | C42: 130001.96 | D42: 0.15 | E42: 1500022.6
A43: 2250033.9 | B43: 4500067.7 | C43: 242503.65 | D43: 0.19 | E43: 2250033.9
A44: 4500067.7 | B44: 6750101.5 | C44: 670010.08 | D44: 0.23 | E44: 4500067.7
A45: 6750101.5 | B45: 10125152 | C45: 1187517.9 | D45: 0.27 | E45: 6750101.5
A46: 10125152 | B46: 15187728 | C46: 2098781.6 | D46: 0.31 | E46: 10125152
A47: 15187728 | B47: en adelante | C47: 3668180.2 | D47: 0.35 | E47: 15187728
A48: =+A38+1 -> 4 | B48: =+B38+1 -> 4 | C48: =+C38+1 -> 4 | E48: =+E38+1 -> 4
A49: 0 | B49: 666676.7 | C49: 0 | D49: 0.05 | E49: 0
A50: 666676.7 | B50: 1333353.4 | C50: 33333.83 | D50: 0.09 | E50: 666676.7
A51: 1333353.4 | B51: 2000030.1 | C51: 93334.74 | D51: 0.12 | E51: 1333353.4
A52: 2000030.1 | B52: 3000045.1 | C52: 173335.94 | D52: 0.15 | E52: 2000030.1
A53: 3000045.1 | B53: 6000090.3 | C53: 323338.2 | D53: 0.19 | E53: 3000045.1
A54: 6000090.3 | B54: 9000135.4 | C54: 893346.77 | D54: 0.23 | E54: 6000090.3
A55: 9000135.4 | B55: 13500203 | C55: 1583357.1 | D55: 0.27 | E55: 9000135.4
A56: 13500203 | B56: 20250305 | C56: 2798375.4 | D56: 0.31 | E56: 13500203
A57: 20250305 | B57: en adelante | C57: 4890906.9 | D57: 0.35 | E57: 20250305
A58: =+A48+1 -> 5 | B58: =+B48+1 -> 5 | C58: =+C48+1 -> 5 | E58: =+E48+1 -> 5
A59: 0 | B59: 833345.87 | C59: 0 | D59: 0.05 | E59: 0
A60: 833345.87 | B60: 1666691.7 | C60: 41667.29 | D60: 0.09 | E60: 833345.87
A61: 1666691.7 | B61: 2500037.6 | C61: 116668.42 | D61: 0.12 | E61: 1666691.7
A62: 2500037.6 | B62: 3750056.4 | C62: 216669.93 | D62: 0.15 | E62: 2500037.6
A63: 3750056.4 | B63: 7500112.8 | C63: 404172.75 | D63: 0.19 | E63: 3750056.4
A64: 7500112.8 | B64: 11250169 | C64: 1116683.5 | D64: 0.23 | E64: 7500112.8
A65: 11250169 | B65: 16875254 | C65: 1979196.4 | D65: 0.27 | E65: 11250169
A66: 16875254 | B66: 25312881 | C66: 3497969.3 | D66: 0.31 | E66: 16875254
A67: 25312881 | B67: en adelante | C67: 6113633.6 | D67: 0.35 | E67: 25312881
A68: =+A58+1 -> 6 | B68: =+B58+1 -> 6 | C68: =+C58+1 -> 6 | E68: =+E58+1 -> 6
A69: 0 | B69: 1000015 | C69: 0 | D69: 0.05 | E69: 0
A70: 1000015 | B70: 2000030.1 | C70: 50000.75 | D70: 0.09 | E70: 1000015
A71: 2000030.1 | B71: 3000045.1 | C71: 140002.11 | D71: 0.12 | E71: 2000030.1
A72: 3000045.1 | B72: 4500067.7 | C72: 260003.91 | D72: 0.15 | E72: 3000045.1
A73: 4500067.7 | B73: 9000135.4 | C73: 485007.3 | D73: 0.19 | E73: 4500067.7
A74: 9000135.4 | B74: 13500203 | C74: 1340020.2 | D74: 0.23 | E74: 9000135.4
A75: 13500203 | B75: 20250305 | C75: 2375035.7 | D75: 0.27 | E75: 13500203
A76: 20250305 | B76: 30375457 | C76: 4197563.2 | D76: 0.31 | E76: 20250305
A77: 30375457 | B77: en adelante | C77: 7336360.4 | D77: 0.35 | E77: 30375457
A78: =+A68+1 -> 7 | B78: =+B68+1 -> 7 | C78: =+C68+1 -> 7 | E78: =+E68+1 -> 7
A79: 0 | B79: 906010.96 | C79: 0 | D79: 0.05 | E79: 0
A80: 906010.96 | B80: 1812021.9 | C80: 45300.55 | D80: 0.09 | E80: 906010.96
A81: 1812021.9 | B81: 2718032.9 | C81: 126841.53 | D81: 0.12 | E81: 1812021.9
A82: 2718032.9 | B82: 4077049.3 | C82: 235562.85 | D82: 0.15 | E82: 2718032.9
A83: 4077049.3 | B83: 8154098.6 | C83: 439415.31 | D83: 0.19 | E83: 4077049.3
A84: 8154098.6 | B84: 12231148 | C84: 1214054.7 | D84: 0.23 | E84: 8154098.6
A85: 12231148 | B85: 18346722 | C85: 2151776 | D85: 0.27 | E85: 12231148
A86: 18346722 | B86: 27520083 | C86: 3802981 | D86: 0.31 | E86: 18346722
A87: 27520083 | B87: en adelante | C87: 6646722.9 | D87: 0.35 | E87: 27520083
A88: =+A78+1 -> 8 | B88: =+B78+1 -> 8 | C88: =+C78+1 -> 8 | E88: =+E78+1 -> 8
A89: 0 | B89: 1051836.1 | C89: 0 | D89: 0.05 | E89: 0
A90: 1051836.1 | B90: 2103672.1 | C90: 52591.8 | D90: 0.09 | E90: 1051836.1
A91: 2103672.1 | B91: 3155508.2 | C91: 147257.05 | D91: 0.12 | E91: 2103672.1
A92: 3155508.2 | B92: 4733262.3 | C92: 273477.38 | D92: 0.15 | E92: 3155508.2
A93: 4733262.3 | B93: 9466524.7 | C93: 510140.5 | D93: 0.19 | E93: 4733262.3
A94: 9466524.7 | B94: 14199787 | C94: 1409460.3 | D94: 0.23 | E94: 9466524.7
A95: 14199787 | B95: 21299681 | C95: 2498110.7 | D95: 0.27 | E95: 14199787
A96: 21299681 | B96: 31949521 | C96: 4415081.9 | D96: 0.31 | E96: 21299681
A97: 31949521 | B97: en adelante | C97: 7716532.4 | D97: 0.35 | E97: 31949521
A98: =+A88+1 -> 9 | B98: =+B88+1 -> 9 | C98: =+C88+1 -> 9 | E98: =+E88+1 -> 9
A99: 0 | B99: 1197661.2 | C99: 0 | D99: 0.05 | E99: 0
A100: 1197661.2 | B100: 2395322.4 | C100: 59883.06 | D100: 0.09 | E100: 1197661.2
A101: 2395322.4 | B101: 3592983.6 | C101: 167672.57 | D101: 0.12 | E101: 2395322.4
A102: 3592983.6 | B102: 5389475.4 | C102: 311391.91 | D102: 0.15 | E102: 3592983.6
A103: 5389475.4 | B103: 10778951 | C103: 580865.68 | D103: 0.19 | E103: 5389475.4
A104: 10778951 | B104: 16168426 | C104: 1604866 | D104: 0.23 | E104: 10778951
A105: 16168426 | B105: 24252639 | C105: 2844445.3 | D105: 0.27 | E105: 16168426
...

Sheet Tablas 
A1: Tabla de Deducciones | N1: https://www.afip.gob.ar/gananciasYBienes/ganancias/personas-humanas-sucesiones-indivisas/deducciones/documentos/Deducciones-personales-art-30-enero-junio-2025.pdf
B2: 1 | C2: 2 | D2: 3 | E2: 4 | F2: 5 | G2: 6 | H2: 7 | I2: 8 | J2: 9 | K2: 10 | L2: 11 | M2: 12 | N2: 13
A3: Ganancia No Imponible | B3: =+$N$3/12*B2 -> 429316.88 | C3: =+$N$3/12*C2 -> 858633.75 | D3: =+$N$3/12*D2 -> 1287950.6 | E3: =+$N$3/12*E2 -> 1717267.5 | F3: =+$N$3/12*F2 -> 2146584.4 | G3: =+$N$3/12*G2 -> 2575901.2 | H3: =+$N$3/12*H2 -> 3005218.1 | I3: =+$N$3/12*I2 -> 3434535 | ... M3: =+$N$3/12*M2 -> 5151802.5 | N3: 5151802.5 | O3: 5151802.5 | P3: GNI
A4: Deducción Especial | B4: =+$N$4/12*B2 -> 2060721 | C4: =+$N$4/12*C2 -> 4121442 | D4: =+$N$4/12*D2 -> 6182163 | E4: =+$N$4/12*E2 -> 8242884 | F4: =+$N$4/12*F2 -> 10303605 | G4: =+$N$4/12*G2 -> 12364326 | H4: =+$N$4/12*H2 -> 14425047 | I4: =+$N$4/12*I2 -> 16485768 | ... M4: =+$N$4/12*M2 -> 24728652 | N4: 24728652 | O4: 24728652 | P4: Deducción especial
A5: Cónyuge | B5: =+$N$5/12*B2 -> 404330.39 | C5: =+$N$5/12*C2 -> 808660.78 | D5: =+$N$5/12*D2 -> 1212991.2 | E5: =+$N$5/12*E2 -> 1617321.6 | F5: =+$N$5/12*F2 -> 2021651.9 | G5: =+$N$5/12*G2 -> 2425982.3 | H5: =+$N$5/12*H2 -> 2830312.7 | I5: =+$N$5/12*I2 -> 3234643.1 | ... M5: =+$N$5/12*M2 -> 4851964.7 | N5: 4851964.7 | O5: 4851964.7 | P5: =N5/O5 -> 1
A6: Hijos | B6: =+$N$6/12*B2 -> 203905.29 | C6: =+$N$6/12*C2 -> 407810.58 | D6: =+$N$6/12*D2 -> 611715.87 | E6: =+$N$6/12*E2 -> 815621.16 | F6: =+$N$6/12*F2 -> 1019526.5 | G6: =+$N$6/12*G2 -> 1223431.7 | H6: =+$N$6/12*H2 -> 1427337 | I6: =+$N$6/12*I2 -> 1631242.3 | ... M6: =+$N$6/12*M2 -> 2446863.5 | N6: 2446863.5 | O6: 2000447.9 | P6: =1-P5 -> 0
A7: Serv Doméstico | B7: =+$N$7/12*B2 -> 257586.25 | C7: =+$N$7/12*C2 -> 515172.5 | D7: =+$N$7/12*D2 -> 772758.75 | E7: =+$N$7/12*E2 -> 1030345 | F7: =+$N$7/12*F2 -> 1287931.2 | G7: =+$N$7/12*G2 -> 1545517.5 | H7: =+$N$7/12*H2 -> 1803103.8 | I7: =+$N$7/12*I2 -> 2060690 | J7: 2318276.2 | K7: 2575862.5 | L7: =+$N$7/12*L2 -> 2833448.8 | M7: =+$N$7/12*M2 -> 3091035 | N7: 3091035
A8: Primas de Seguro | B8: =+$N$8/12*B2 -> 13896.5 | C8: =+$N$8/12*C2 -> 27793 | D8: =+$N$8/12*D2 -> 41689.5 | E8: =+$N$8/12*E2 -> 55586 | F8: =+$N$8/12*F2 -> 69482.5 | G8: =+$N$8/12*G2 -> 83379 | H8: =+$N$8/12*H2 -> 97275.5 | I8: =+$N$8/12*I2 -> 111172 | J8: 125068.5 | K8: 138965 | L8: =+$N$8/12*L2 -> 152861.5 | M8: =+$N$8/12*M2 -> 166758 | N8: 166758
A9: Gastos Educación | B9: =+$N$9/12*B2 -> 103034.5 | C9: =+$N$9/12*C2 -> 206069 | D9: =+$N$9/12*D2 -> 309103.5 | E9: =+$N$9/12*E2 -> 412138 | F9: =+$N$9/12*F2 -> 515172.5 | G9: =+$N$9/12*G2 -> 618207 | H9: =+$N$9/12*H2 -> 721241.5 | I9: =+$N$9/12*I2 -> 824276 | J9: 927310.5 | K9: 1030345 | L9: =+$N$9/12*L2 -> 1133379.5 | M9: =+$N$9/12*M2 -> 1236414 | N9: 1236414
L10: =SUM(L3:L6) -> 34081009
L11: =L10/12 -> 2840084.1
B12: Prima Seguro | C12: Gastos | D12: Intereses | E12: Serv Doméstico | F12: Educación
A13: Mes | C13: Sepelio | D13: Hipotecarios
A14: 1 | B14: 83.01 | C14: 83.01 | D14: 1666.67 | E14: =+$N$7/12*A14 -> 257586.25 | F14: =+$N$9/12*A14 -> 103034.5
A15: 2 | B15: 166.02 | C15: 166.02 | D15: 3333.33 | E15: =+$N$7/12*A15 -> 515172.5 | F15: =+$N$9/12*A15 -> 206069
A16: 3 | B16: 249.03 | C16: 249.03 | D16: 5000 | E16: =+$N$7/12*A16 -> 772758.75 | F16: =+$N$9/12*A16 -> 309103.5
A17: 4 | B17: 332.04 | C17: 332.04 | D17: 6666.67 | E17: =+$N$7/12*A17 -> 1030345 | F17: =+$N$9/12*A17 -> 412138
A18: 5 | B18: 415.05 | C18: 415.05 | D18: 8333.33 | E18: =+$N$7/12*A18 -> 1287931.2 | F18: =+$N$9/12*A18 -> 515172.5
A19: 6 | B19: 498.06 | C19: 498.06 | D19: 10000 | E19: =+$N$7/12*A19 -> 1545517.5 | F19: =+$N$9/12*A19 -> 618207
A20: 7 | B20: 581.07 | C20: 581.07 | D20: 11666.67 | E20: =+$N$7/12*A20 -> 1803103.8 | F20: =+$N$9/12*A20 -> 721241.5
A21: 8 | B21: 664.08 | C21: 664.08 | D21: 13333.33 | E21: =+$N$7/12*A21 -> 2060690 | F21: =+$N$9/12*A21 -> 824276
A22: 9 | B22: 747.09 | C22: 747.09 | D22: 15000 | E22: =+$N$7/12*A22 -> 2318276.2 | F22: =+$N$9/12*A22 -> 927310.5
A23: 10 | B23: 830.1 | C23: 830.1 | D23: 16666.67 | E23: =+$N$7/12*A23 -> 2575862.5 | F23: =+$N$9/12*A23 -> 1030345
A24: 11 | B24: 913.11 | C24: 913.11 | D24: 18333.33 | E24: =+$N$7/12*A24 -> 2833448.8 | F24: =+$N$9/12*A24 -> 1133379.5
A25: 12 | B25: 996.12 | C25: 996.12 | D25: 20000 | E25: =+$N$7/12*A25 -> 3091035 | F25: =+$N$9/12*A25 -> 1236414
